silero_vad_nuaazs/__init__.py
silero_vad_nuaazs/cli.py
silero_vad_nuaazs/frame_queue.py
silero_vad_nuaazs/inference_session.py
silero_vad_nuaazs/silero_vad.onnx
silero_vad_nuaazs/silero_vad.py
silero_vad_nuaazs/utils.py
silero_vad_nuaazs-0.0.4.dist-info/LICENSE
silero_vad_nuaazs-0.0.4.dist-info/METADATA
silero_vad_nuaazs-0.0.4.dist-info/WHEEL
silero_vad_nuaazs-0.0.4.dist-info/entry_points.txt
silero_vad_nuaazs-0.0.4.dist-info/top_level.txt
silero_vad_nuaazs-0.0.4.dist-info/RECORD
