Metadata-Version: 2.1
Name: silero-vad-nuaazs
Version: 0.0.4
Summary: Silero VAD
Home-page: https://github.com/pengzhendong/silero-vad
Author: Zhendong Peng
Author-email: pzd17@tsinghua.org.cn
Classifier: Programming Language :: Python :: 3
Classifier: Operating System :: OS Independent
Classifier: Topic :: Scientific/Engineering
License-File: LICENSE
Requires-Dist: librosa
Requires-Dist: numpy
Requires-Dist: onnxruntime
Requires-Dist: soxr
Requires-Dist: praat-parselmouth
